opengpt/README.md
opengpt/__init__.py
opengpt/config.yml
opengpt/libraries/colorama/__init__.py
opengpt/libraries/colorama/ansi.py
opengpt/libraries/colorama/ansitowin32.py
opengpt/libraries/colorama/initialise.py
opengpt/libraries/colorama/win32.py
opengpt/libraries/colorama/winterm.py
opengpt/libraries/tempmail.py
opengpt/models/completion/chatbase/DOC.md
opengpt/models/completion/chatbase/README.md
opengpt/models/completion/chatbase/model.py
opengpt/models/completion/chatgptproxy/DOC.md
opengpt/models/completion/chatgptproxy/README.md
opengpt/models/completion/chatgptproxy/model.py
opengpt/models/completion/chatllama/DOC.md
opengpt/models/completion/chatllama/README.md
opengpt/models/completion/chatllama/model.py
opengpt/models/completion/forefront/DOC.md
opengpt/models/completion/forefront/README.md
opengpt/models/completion/forefront/attributes/conversation.py
opengpt/models/completion/forefront/model.py
opengpt/models/completion/forefront/tools/system/email_creation.py
opengpt/models/completion/forefront/tools/system/signature.py
opengpt/models/completion/forefront/tools/typing/response.py
opengpt/models/completion/italygpt/DOC.md
opengpt/models/completion/italygpt/README.md
opengpt/models/completion/italygpt/model.py
opengpt/models/completion/usesless/DOC.md
opengpt/models/completion/usesless/README.md
opengpt/models/completion/usesless/model.py
opengpt/models/completion/usesless/tools/typing/response.py
opengpt/models/image/hotpot/model.py
opengpt/models/image/hotpot/styles.yml
opengpt/models/image/hotpot/tools/system/id.py
opengpt/models/image/hotpot/tools/typing/response.py
opengpt4-0.1.8.dist-info/LICENSE
opengpt4-0.1.8.dist-info/METADATA
opengpt4-0.1.8.dist-info/WHEEL
opengpt4-0.1.8.dist-info/RECORD
