Metadata-Version: 2.1
Name: opengpt4
Version: 0.1.8
Summary: OpenGPT 3.5/4 is a project aimed at providing practical and user-friendly APIs. The APIs allow for easy integration with various applications, making it simple for developers to incorporate the natural language processing capabilities of GPT into their projects.
License: GPL-3.0
Requires-Python: >=3.7,<4.0
Classifier: License :: OSI Approved :: GNU General Public License v3 (GPLv3)
Classifier: Programming Language :: Python :: 3
Classifier: Programming Language :: Python :: 3.7
Classifier: Programming Language :: Python :: 3.8
Classifier: Programming Language :: Python :: 3.9
Classifier: Programming Language :: Python :: 3.10
Classifier: Programming Language :: Python :: 3.11
Requires-Dist: PyYAML (==6.0)
Requires-Dist: fake-useragent (==1.1.3)
Requires-Dist: pydantic (==1.10.7)
Requires-Dist: requests (==2.28.2)
Requires-Dist: tls-client (==0.2)
